kong_service_exporter/__init__.py
kong_service_exporter/generate.py
kong_service_exporter/main.py
kong_service_exporter/template.md
kong_service_exporter-0.1.1.dist-info/LICENSE
kong_service_exporter-0.1.1.dist-info/METADATA
kong_service_exporter-0.1.1.dist-info/WHEEL
kong_service_exporter-0.1.1.dist-info/entry_points.txt
kong_service_exporter-0.1.1.dist-info/top_level.txt
kong_service_exporter-0.1.1.dist-info/RECORD
