Metadata-Version: 2.1
Name: kong-service-exporter
Version: 0.1.1
Summary: A small utility to export a Markdown file containing the list of services and other useful information from Kong's config.
Home-page: https://github.com/mr-karan/kong-service-exporter
Author: Karan Sharma
Author-email: hello@mrkaran.dev
License: MIT License
Download-URL: https://github.com/mr-karan/kong-service-exporter
Platform: UNKNOWN
Classifier: Topic :: Documentation
Requires-Dist: Jinja2 (==2.11.3)
Requires-Dist: PyYAML (==5.4.1)
